LICENSE
README.md
setup.py
upstreet/__init__.py
upstreet/bot.py
upstreet/main.py
upstreet.egg-info/PKG-INFO
upstreet.egg-info/SOURCES.txt
upstreet.egg-info/dependency_links.txt
upstreet.egg-info/top_level.txt