Metadata-Version: 2.1
Name: upstreet
Version: 1.13.2
Summary: SDK for interacting with Upstreet.
Home-page: https://github.com/M3-org/upstreet-sdk
Author: Moon
Author-email: shawmakesmagic@gmail.com
License: MIT
Classifier: Development Status :: 4 - Beta
Classifier: Intended Audience :: Science/Research
Classifier: License :: OSI Approved :: MIT License
Classifier: Operating System :: POSIX :: Linux
Classifier: Programming Language :: Python :: 3
Classifier: Operating System :: MacOS :: MacOS X
Classifier: Operating System :: Microsoft :: Windows
License-File: LICENSE
